lob/__init__.py
lob/api_helper.py
lob/configuration.py
lob/lob_client.py
lob/controllers/__init__.py
lob/controllers/addresses_controller.py
lob/controllers/bank_accounts_controller.py
lob/controllers/base_controller.py
lob/controllers/billing_groups_controller.py
lob/controllers/buckslip_orders_controller.py
lob/controllers/buckslips_controller.py
lob/controllers/campaigns_controller.py
lob/controllers/card_orders_controller.py
lob/controllers/cards_controller.py
lob/controllers/checks_controller.py
lob/controllers/creatives_controller.py
lob/controllers/identity_validation_controller.py
lob/controllers/intl_autocompletions_controller.py
lob/controllers/intl_verifications_controller.py
lob/controllers/letters_controller.py
lob/controllers/postcards_controller.py
lob/controllers/qr_codes_controller.py
lob/controllers/reverse_geocode_lookups_controller.py
lob/controllers/self_mailers_controller.py
lob/controllers/template_versions_controller.py
lob/controllers/templates_controller.py
lob/controllers/uploads_controller.py
lob/controllers/url_shortener_controller.py
lob/controllers/us_autocompletions_controller.py
lob/controllers/us_verifications_controller.py
lob/controllers/zip_lookups_controller.py
lob/exceptions/__init__.py
lob/exceptions/api_exception.py
lob/exceptions/domains_0_error_1_exception.py
lob/exceptions/domains_links_0_error_1_exception.py
lob/exceptions/http_validation_error_1_exception.py
lob/exceptions/links_0_error_1_exception.py
lob/exceptions/upload_export_error_1_exception.py
lob/exceptions/uploads_report_403_error_exception.py
lob/http/__init__.py
lob/http/http_call_back.py
lob/http/http_method_enum.py
lob/http/http_request.py
lob/http/http_response.py
lob/http/auth/__init__.py
lob/http/auth/basic_auth.py
lob/models/__init__.py
lob/models/account_type_enum.py
lob/models/address_country_1_enum.py
lob/models/address_country_2_enum.py
lob/models/address_country_enum.py
lob/models/address_deletion.py
lob/models/address_editable_intl.py
my_package_sdkwewqe-4.5.5.dist-info/LICENSE
my_package_sdkwewqe-4.5.5.dist-info/METADATA
my_package_sdkwewqe-4.5.5.dist-info/WHEEL
my_package_sdkwewqe-4.5.5.dist-info/top_level.txt
my_package_sdkwewqe-4.5.5.dist-info/RECORD
