Metadata-Version: 2.1
Name: my-package-sdkwewqe
Version: 4.5.5
Summary: test
Author-email: Zahra <zahra.naseem@apimatic.io>
Project-URL: Documentation, https://apimatic.io
Requires-Python: >=3.7
License-File: LICENSE
Requires-Dist: apimatic-core >=0.2.15,~=0.2.0
Requires-Dist: apimatic-core-interfaces >=0.1.5,~=0.1.0
Requires-Dist: apimatic-requests-client-adapter >=0.1.6,~=0.1.0
Requires-Dist: python-dateutil ~=2.8.1
Requires-Dist: jsonschema ~=3.2.0
Provides-Extra: testutils
Requires-Dist: pytest >=7.2.2 ; extra == 'testutils'
